simple_mock_server/__init__.py
simple_mock_server/config_parser.py
simple_mock_server/server.py
simple_mock_server/core/__init__.py
simple_mock_server/core/auth.py
simple_mock_server/core/metrics.py
simple_mock_server/core/rate_limiter.py
simple_mock_server/core/response.py
simple_api_mock_server-0.3.3.dist-info/LICENSE
simple_api_mock_server-0.3.3.dist-info/METADATA
simple_api_mock_server-0.3.3.dist-info/WHEEL
simple_api_mock_server-0.3.3.dist-info/entry_points.txt
simple_api_mock_server-0.3.3.dist-info/top_level.txt
simple_api_mock_server-0.3.3.dist-info/RECORD
