Metadata-Version: 2.1
Name: simple-api-mock-server
Version: 0.3.3
Summary: A simple, file-based API mocking server.
Home-page: https://github.com/sanatladkat/simple-api-mock-server
Author: Sanat Ladkat
Author-email: Sanat Ladkat <arsanatladkat@gmail.com>
Project-URL: Homepage, https://github.com/sanatladkat/simple-api-mock-server
Project-URL: Bug Tracker, https://github.com/sanatladkat/simple-api-mock-server/issues
Classifier: Programming Language :: Python :: 3
Classifier: License :: OSI Approved :: MIT License
Classifier: Operating System :: OS Independent
Classifier: Framework :: Flask
Classifier: Topic :: Software Development :: Testing
Classifier: Topic :: Internet :: WWW/HTTP :: HTTP Servers
Requires-Python: >=3.7
License-File: LICENSE
Requires-Dist: Flask
Requires-Dist: jsonschema
Requires-Dist: watchdog
Requires-Dist: Flask-Cors
Requires-Dist: PyYAML
Provides-Extra: dev
Requires-Dist: requests ; extra == 'dev'
Requires-Dist: pytest ; extra == 'dev'
